[
  {
    "row_index": 25,
    "chart_id": "1gb8sqnptdsdvagz",
    "question": "Find the difference between the average of the first three years of the male group and the average of the last three yea",
    "issues": [
      "all ops groups are empty ({\"ops\":[]} fallback)"
    ]
  },
  {
    "row_index": 26,
    "chart_id": "",
    "question": "Find a hair removal type with a share of 10% or more in the under 30s group",
    "issues": [
      "operation_spec is empty"
    ]
  },
  {
    "row_index": 111,
    "chart_id": "19xwo5oscmgpcdyl",
    "question": "What the average of the agricultural values for all years in which the value of industry is greater than 0.2?",
    "issues": [
      "all ops groups are empty ({\"ops\":[]} fallback)"
    ]
  },
  {
    "row_index": 116,
    "chart_id": "19msoowya2szdynd",
    "question": "What is the sum of the Coal values for all years in which the value of Gas is greater than 1/3 of the value of Oil?",
    "issues": [
      "all ops groups are empty ({\"ops\":[]} fallback)"
    ]
  },
  {
    "row_index": 142,
    "chart_id": "1fngt6cb1d60a2ow",
    "question": "Does the value of all regions except Metro Total exceed 50,000?",
    "issues": [
      "ops2: compareBool: targetB=50000 not in Number of employees values (have ['11580', '11583', '23483', '27681', '7054', '7182']…)"
    ]
  }
]